LICENSE
MANIFEST.in
README.md
dev-requirements.txt
pyproject.toml
requirements.txt
setup.cfg
setup.py
versioneer.py
docs/fidescls/docs/installation/pypi.md
fidescls/__init__.py
fidescls/_version.py
fidescls.egg-info/PKG-INFO
fidescls.egg-info/SOURCES.txt
fidescls.egg-info/dependency_links.txt
fidescls.egg-info/entry_points.txt
fidescls.egg-info/requires.txt
fidescls.egg-info/top_level.txt
fidescls/api/__init__.py
fidescls/api/classify.py
fidescls/api/config.py
fidescls/api/logger.py
fidescls/api/main.py
fidescls/api/models.py
fidescls/api/logs/__init__.py
fidescls/cli/__init__.py
fidescls/cli/api.py
fidescls/cli/classify.py
fidescls/cli/config.py
fidescls/cli/context.py
fidescls/cli/logger.py
fidescls/cli/options.py
fidescls/cli/scan.py
fidescls/cli/logs/__init__.py
fidescls/cls/__init__.py
fidescls/cls/aggregation.py
fidescls/cls/classifiers.py
fidescls/cls/config.py
fidescls/cls/content.py
fidescls/cls/context.py
fidescls/cls/decision.py
fidescls/cls/entity_map.py
fidescls/cls/models.py
fidescls/cls/scan.py
fidescls/utils/__init__.py
fidescls/utils/databases.py
fidescls/utils/fides_nlp.py