Metadata-Version: 2.1
Name: fidescls
Version: 0.9.2
Summary: CLI for Fidescls
Home-page: https://github.com/ethyca/fidescls
Author: Ethyca, Inc.
Author-email: fidesteam@ethyca.com
License: Apache License 2.0
Platform: UNKNOWN
Classifier: License :: OSI Approved :: Apache Software License
Classifier: Programming Language :: Python :: 3 :: Only
Classifier: Programming Language :: Python :: 3.8
Classifier: Programming Language :: Python :: 3.9
Classifier: Topic :: Software Development :: Libraries
Requires-Python: >=3.8, <4
